src/__init__.py
src/ipay/__init__.py
src/ipay/domain/__init__.py
src/ipay/domain/data.py
src/ipay/domain/data1.py
src/ipay/services/__init__.py
src/ipay/services/c2b.py
src/ipay/services/c2b1.py
src/ipay/utils/__init__.py
src/ipay/utils/base_utils.py
src/ipay/utils/http_client.py
src/tests/__init__.py
src/tests/domain_tests.py
src/tests/services_test.py
python_ipay-0.1.0.dist-info/LICENSE
python_ipay-0.1.0.dist-info/METADATA
python_ipay-0.1.0.dist-info/WHEEL
python_ipay-0.1.0.dist-info/top_level.txt
python_ipay-0.1.0.dist-info/RECORD
