Metadata-Version: 2.1
Name: python-ipay
Version: 0.1.0
Summary: A python library for ipay.
Home-page: https://github.com/Softech-Technologies/ipay
Author: Jamie Omondi
Author-email: cruiseomondi90@gmail.com
License: MIT License
Classifier: Programming Language :: Python :: 3.8
Classifier: License :: OSI Approved :: MIT License
Classifier: Operating System :: OS Independent
License-File: LICENSE
Requires-Dist: requests
Requires-Dist: setuptools
Requires-Dist: wheel
Requires-Dist: twine
Requires-Dist: pytest
Requires-Dist: pylint
